agentk/__init__.py
agentk/__main__.py
agentk/council.py
agentk/llm.py
agentk/scout.py
agentk/tools.py
agentk8-2.3.8.dist-info/licenses/LICENSE
agentk8-2.3.8.dist-info/METADATA
agentk8-2.3.8.dist-info/WHEEL
agentk8-2.3.8.dist-info/entry_points.txt
agentk8-2.3.8.dist-info/top_level.txt
agentk8-2.3.8.dist-info/RECORD
