Metadata-Version: 2.4
Name: agentk8
Version: 2.3.8
Summary: Multi-LLM Council Backend for AGENT-K - Three-stage consensus with GPT, Gemini, and Claude
Author-email: Aditya Katiyar <aditya@example.com>
License: MIT
Project-URL: Homepage, https://github.com/de5truct0/agentk
Project-URL: Documentation, https://github.com/de5truct0/agentk#readme
Project-URL: Repository, https://github.com/de5truct0/agentk.git
Project-URL: Issues, https://github.com/de5truct0/agentk/issues
Keywords: claude,claude-code,gpt,gemini,ai,agents,multi-agent,llm,council,consensus,litellm,cli,terminal,developer-tools,ml,machine-learning
Classifier: Development Status :: 4 - Beta
Classifier: Environment :: Console
Classifier: Intended Audience :: Developers
Classifier: License :: OSI Approved :: MIT License
Classifier: Operating System :: MacOS
Classifier: Operating System :: POSIX :: Linux
Classifier: Programming Language :: Python :: 3
Classifier: Programming Language :: Python :: 3.10
Classifier: Programming Language :: Python :: 3.11
Classifier: Programming Language :: Python :: 3.12
Classifier: Topic :: Software Development
Classifier: Topic :: Scientific/Engineering :: Artificial Intelligence
Requires-Python: >=3.10
License-File: LICENSE
Requires-Dist: litellm>=1.50.0
Requires-Dist: python-dotenv>=1.0.0
Requires-Dist: pathspec>=0.12.0
Requires-Dist: aiohttp>=3.9.0
Provides-Extra: dev
Requires-Dist: pytest>=8.0.0; extra == "dev"
Requires-Dist: pytest-asyncio>=0.23.0; extra == "dev"
Dynamic: license-file
